slow_learner_convert/__init__.py
slow_learner_convert/cli.py
slow_learner_convert/constructor.py
slow_learner_convert-0.2.0.dist-info/METADATA
slow_learner_convert-0.2.0.dist-info/WHEEL
slow_learner_convert-0.2.0.dist-info/entry_points.txt
slow_learner_convert-0.2.0.dist-info/licenses/LICENSE
slow_learner_convert-0.2.0.dist-info/RECORD
