Metadata-Version: 2.1
Name: slow-learner-convert
Version: 0.2.0
Summary: Add your description here
Author-email: Gorka Eraña <eranagorka@gmail.com>
License-File: LICENSE
Requires-Python: >=3.8
Requires-Dist: attrs
Requires-Dist: msgspec
Requires-Dist: pydantic
Requires-Dist: slow-learner
